avasor/base.py
avasor/console.py
avasor/roles/borg_role.py
avasor/roles/role.py
avasor/roles/status_role.py
avasor/server.py
avasor-0.1.0.dist-info/LICENSE
avasor-0.1.0.dist-info/METADATA
avasor-0.1.0.dist-info/WHEEL
avasor-0.1.0.dist-info/RECORD
