Metadata-Version: 2.1
Name: avasor
Version: 0.1.0
Summary: 
Author: Robert Bock
Requires-Python: >=3.10,<4.0
Classifier: Programming Language :: Python :: 3
Classifier: Programming Language :: Python :: 3.10
Classifier: Programming Language :: Python :: 3.11
Classifier: Programming Language :: Python :: 3.12
Requires-Dist: psutil (>=5.9.7,<6.0.0)
